[{"name":"অ্যাসিস্ট্যান্ট প্রফেসর ডাঃ মোঃ রাইসুল আবেদিন","Degree":"এমবিবিএস (ঢাকা),এফসিপিএস (সার্জারি),  জেনারেল ও ল্যাপারোস্কোপিক সার্জন","Address":"সার্জারি বিভাগ,ঢাকা মেডিকেল কলেজ","Visit":"সাক্ষাৎঃশনিবার ও বুধবার বিকাল ৩টা থেকে বিকাল ৫টা পর্যন্ত","phone":"09613-787808"},
{"name":"অ্যাসিস্ট্যান্ট প্রফেসর ডাঃ মোসাঃশাহনাজ পারভীন","Degree":" এমবিবিএস,বিসিএস (স্বাস্থ্য),এফসিপিএস (সার্জারি),","Address":"সরকারি তাজউদ্দীন মেডিকেল কলেজ ও হাসপাতাল,গাজীপুর","Visit":"সাক্ষাৎঃশুক্রবার বিকাল ৩টা থেকে ৬টা পর্যন্ত এবং  সোমবার বিকাল ৫টা থেকে ৭টা পর্যন্ত","phone":"09613-787808"}
]